[{"date":"4/1/2026","modified":"2026-04-01T20:35:02Z","totalCensus":null,"occupancyPct":null,"census1East":null,"census2East":null,"census2West":null,"census3East":null,"census3West":null,"censusHRC":null,"occPct1East":null,"occPct2East":null,"occPct2West":null,"occPct3East":null,"occPct3West":null,"occPctHRC":null,"obsHrs":null,"modelDcEpob":null,"modelTotalEpob":null,"modelVarHrsDay":null,"varAdjFTE":null,"fixedFTE":null,"grandAdjFTE":null,"actualVarHrsDay":null,"actualFixHrsDay":null,"actualOtTotal":null,"actualVarFTE":null,"actualFixFTE":null,"actualTotalFTE":null,"actualDcEpob":null,"actualTotalEpob":null,"varianceHrsDay":null,"variancePct":null,"dcEpobVariance":null,"totalEpobVariance":null,"hasPayrollData":null,"payrollFile":null,"actualHrsDay_1East":null,"actualHC_1East":null,"actualOT_1East":null,"actualNpHrs_1East":null,"modelHrsDay_1East":null,"varianceHrs_1East":null,"variancePct_1East":null,"actualHrsDay_2East":null,"actualHC_2East":null,"actualOT_2East":null,"actualNpHrs_2East":null,"modelHrsDay_2East":null,"varianceHrs_2East":null,"variancePct_2East":null,"actualHrsDay_2West":null,"actualHC_2West":null,"actualOT_2West":null,"actualNpHrs_2West":null,"modelHrsDay_2West":null,"varianceHrs_2West":null,"variancePct_2West":null,"actualHrsDay_3East":null,"actualHC_3East":null,"actualOT_3East":null,"actualNpHrs_3East":null,"modelHrsDay_3East":null,"varianceHrs_3East":null,"variancePct_3East":null,"actualHrsDay_3West":null,"actualHC_3West":null,"actualOT_3West":null,"actualNpHrs_3West":null,"modelHrsDay_3West":null,"varianceHrs_3West":null,"variancePct_3West":null,"actualHrsDay_HRC":null,"actualHC_HRC":null,"actualOT_HRC":null,"actualNpHrs_HRC":null,"modelHrsDay_HRC":null,"varianceHrs_HRC":null,"variancePct_HRC":null,"TimeEntryDate":"2026-03-31"},{"date":"4/2/2026","modified":"2026-04-02T17:18:35Z","totalCensus":null,"occupancyPct":null,"census1East":null,"census2East":null,"census2West":null,"census3East":null,"census3West":null,"censusHRC":null,"occPct1East":null,"occPct2East":null,"occPct2West":null,"occPct3East":null,"occPct3West":null,"occPctHRC":null,"obsHrs":null,"modelDcEpob":null,"modelTotalEpob":null,"modelVarHrsDay":null,"varAdjFTE":null,"fixedFTE":null,"grandAdjFTE":null,"actualVarHrsDay":null,"actualFixHrsDay":null,"actualOtTotal":null,"actualVarFTE":null,"actualFixFTE":null,"actualTotalFTE":null,"actualDcEpob":null,"actualTotalEpob":null,"varianceHrsDay":null,"variancePct":null,"dcEpobVariance":null,"totalEpobVariance":null,"hasPayrollData":null,"payrollFile":null,"actualHrsDay_1East":null,"actualHC_1East":null,"actualOT_1East":null,"actualNpHrs_1East":null,"modelHrsDay_1East":null,"varianceHrs_1East":null,"variancePct_1East":null,"actualHrsDay_2East":null,"actualHC_2East":null,"actualOT_2East":null,"actualNpHrs_2East":null,"modelHrsDay_2East":null,"varianceHrs_2East":null,"variancePct_2East":null,"actualHrsDay_2West":null,"actualHC_2West":null,"actualOT_2West":null,"actualNpHrs_2West":null,"modelHrsDay_2West":null,"varianceHrs_2West":null,"variancePct_2West":null,"actualHrsDay_3East":null,"actualHC_3East":null,"actualOT_3East":null,"actualNpHrs_3East":null,"modelHrsDay_3East":null,"varianceHrs_3East":null,"variancePct_3East":null,"actualHrsDay_3West":null,"actualHC_3West":null,"actualOT_3West":null,"actualNpHrs_3West":null,"modelHrsDay_3West":null,"varianceHrs_3West":null,"variancePct_3West":null,"actualHrsDay_HRC":null,"actualHC_HRC":null,"actualOT_HRC":null,"actualNpHrs_HRC":null,"modelHrsDay_HRC":null,"varianceHrs_HRC":null,"variancePct_HRC":null,"TimeEntryDate":"2026-04-01"},{"date":"4/2/2026","modified":"2026-04-02T20:28:51Z","totalCensus":null,"occupancyPct":null,"census1East":null,"census2East":null,"census2West":null,"census3East":null,"census3West":null,"censusHRC":null,"occPct1East":null,"occPct2East":null,"occPct2West":null,"occPct3East":null,"occPct3West":null,"occPctHRC":null,"obsHrs":null,"modelDcEpob":null,"modelTotalEpob":null,"modelVarHrsDay":null,"varAdjFTE":null,"fixedFTE":null,"grandAdjFTE":null,"actualVarHrsDay":null,"actualFixHrsDay":null,"actualOtTotal":null,"actualVarFTE":null,"actualFixFTE":null,"actualTotalFTE":null,"actualDcEpob":null,"actualTotalEpob":null,"varianceHrsDay":null,"variancePct":null,"dcEpobVariance":null,"totalEpobVariance":null,"hasPayrollData":null,"payrollFile":null,"actualHrsDay_1East":null,"actualHC_1East":null,"actualOT_1East":null,"actualNpHrs_1East":null,"modelHrsDay_1East":null,"varianceHrs_1East":null,"variancePct_1East":null,"actualHrsDay_2East":null,"actualHC_2East":null,"actualOT_2East":null,"actualNpHrs_2East":null,"modelHrsDay_2East":null,"varianceHrs_2East":null,"variancePct_2East":null,"actualHrsDay_2West":null,"actualHC_2West":null,"actualOT_2West":null,"actualNpHrs_2West":null,"modelHrsDay_2West":null,"varianceHrs_2West":null,"variancePct_2West":null,"actualHrsDay_3East":null,"actualHC_3East":null,"actualOT_3East":null,"actualNpHrs_3East":null,"modelHrsDay_3East":null,"varianceHrs_3East":null,"variancePct_3East":null,"actualHrsDay_3West":null,"actualHC_3West":null,"actualOT_3West":null,"actualNpHrs_3West":null,"modelHrsDay_3West":null,"varianceHrs_3West":null,"variancePct_3West":null,"actualHrsDay_HRC":null,"actualHC_HRC":null,"actualOT_HRC":null,"actualNpHrs_HRC":null,"modelHrsDay_HRC":null,"varianceHrs_HRC":null,"variancePct_HRC":null,"TimeEntryDate":"2026-03-02"},{"date":"4/2/2026","modified":"2026-04-02T20:30:31Z","totalCensus":null,"occupancyPct":null,"census1East":null,"census2East":null,"census2West":null,"census3East":null,"census3West":null,"censusHRC":null,"occPct1East":null,"occPct2East":null,"occPct2West":null,"occPct3East":null,"occPct3West":null,"occPctHRC":null,"obsHrs":null,"modelDcEpob":null,"modelTotalEpob":null,"modelVarHrsDay":null,"varAdjFTE":null,"fixedFTE":null,"grandAdjFTE":null,"actualVarHrsDay":null,"actualFixHrsDay":null,"actualOtTotal":null,"actualVarFTE":null,"actualFixFTE":null,"actualTotalFTE":null,"actualDcEpob":null,"actualTotalEpob":null,"varianceHrsDay":null,"variancePct":null,"dcEpobVariance":null,"totalEpobVariance":null,"hasPayrollData":null,"payrollFile":null,"actualHrsDay_1East":null,"actualHC_1East":null,"actualOT_1East":null,"actualNpHrs_1East":null,"modelHrsDay_1East":null,"varianceHrs_1East":null,"variancePct_1East":null,"actualHrsDay_2East":null,"actualHC_2East":null,"actualOT_2East":null,"actualNpHrs_2East":null,"modelHrsDay_2East":null,"varianceHrs_2East":null,"variancePct_2East":null,"actualHrsDay_2West":null,"actualHC_2West":null,"actualOT_2West":null,"actualNpHrs_2West":null,"modelHrsDay_2West":null,"varianceHrs_2West":null,"variancePct_2West":null,"actualHrsDay_3East":null,"actualHC_3East":null,"actualOT_3East":null,"actualNpHrs_3East":null,"modelHrsDay_3East":null,"varianceHrs_3East":null,"variancePct_3East":null,"actualHrsDay_3West":null,"actualHC_3West":null,"actualOT_3West":null,"actualNpHrs_3West":null,"modelHrsDay_3West":null,"varianceHrs_3West":null,"variancePct_3West":null,"actualHrsDay_HRC":null,"actualHC_HRC":null,"actualOT_HRC":null,"actualNpHrs_HRC":null,"modelHrsDay_HRC":null,"varianceHrs_HRC":null,"variancePct_HRC":null,"TimeEntryDate":"2026-03-01"},{"date":"4/2/2026","modified":"2026-04-02T20:30:33Z","totalCensus":null,"occupancyPct":null,"census1East":null,"census2East":null,"census2West":null,"census3East":null,"census3West":null,"censusHRC":null,"occPct1East":null,"occPct2East":null,"occPct2West":null,"occPct3East":null,"occPct3West":null,"occPctHRC":null,"obsHrs":null,"modelDcEpob":null,"modelTotalEpob":null,"modelVarHrsDay":null,"varAdjFTE":null,"fixedFTE":null,"grandAdjFTE":null,"actualVarHrsDay":null,"actualFixHrsDay":null,"actualOtTotal":null,"actualVarFTE":null,"actualFixFTE":null,"actualTotalFTE":null,"actualDcEpob":null,"actualTotalEpob":null,"varianceHrsDay":null,"variancePct":null,"dcEpobVariance":null,"totalEpobVariance":null,"hasPayrollData":null,"payrollFile":null,"actualHrsDay_1East":null,"actualHC_1East":null,"actualOT_1East":null,"actualNpHrs_1East":null,"modelHrsDay_1East":null,"varianceHrs_1East":null,"variancePct_1East":null,"actualHrsDay_2East":null,"actualHC_2East":null,"actualOT_2East":null,"actualNpHrs_2East":null,"modelHrsDay_2East":null,"varianceHrs_2East":null,"variancePct_2East":null,"actualHrsDay_2West":null,"actualHC_2West":null,"actualOT_2West":null,"actualNpHrs_2West":null,"modelHrsDay_2West":null,"varianceHrs_2West":null,"variancePct_2West":null,"actualHrsDay_3East":null,"actualHC_3East":null,"actualOT_3East":null,"actualNpHrs_3East":null,"modelHrsDay_3East":null,"varianceHrs_3East":null,"variancePct_3East":null,"actualHrsDay_3West":null,"actualHC_3West":null,"actualOT_3West":null,"actualNpHrs_3West":null,"modelHrsDay_3West":null,"varianceHrs_3West":null,"variancePct_3West":null,"actualHrsDay_HRC":null,"actualHC_HRC":null,"actualOT_HRC":null,"actualNpHrs_HRC":null,"modelHrsDay_HRC":null,"varianceHrs_HRC":null,"variancePct_HRC":null,"TimeEntryDate":"2026-03-03"},{"date":"4/2/2026","modified":"2026-04-02T20:40:40Z","totalCensus":null,"occupancyPct":null,"census1East":null,"census2East":null,"census2West":null,"census3East":null,"census3West":null,"censusHRC":null,"occPct1East":null,"occPct2East":null,"occPct2West":null,"occPct3East":null,"occPct3West":null,"occPctHRC":null,"obsHrs":null,"modelDcEpob":null,"modelTotalEpob":null,"modelVarHrsDay":null,"varAdjFTE":null,"fixedFTE":null,"grandAdjFTE":null,"actualVarHrsDay":null,"actualFixHrsDay":null,"actualOtTotal":null,"actualVarFTE":null,"actualFixFTE":null,"actualTotalFTE":null,"actualDcEpob":null,"actualTotalEpob":null,"varianceHrsDay":null,"variancePct":null,"dcEpobVariance":null,"totalEpobVariance":null,"hasPayrollData":null,"payrollFile":null,"actualHrsDay_1East":null,"actualHC_1East":null,"actualOT_1East":null,"actualNpHrs_1East":null,"modelHrsDay_1East":null,"varianceHrs_1East":null,"variancePct_1East":null,"actualHrsDay_2East":null,"actualHC_2East":null,"actualOT_2East":null,"actualNpHrs_2East":null,"modelHrsDay_2East":null,"varianceHrs_2East":null,"variancePct_2East":null,"actualHrsDay_2West":null,"actualHC_2West":null,"actualOT_2West":null,"actualNpHrs_2West":null,"modelHrsDay_2West":null,"varianceHrs_2West":null,"variancePct_2West":null,"actualHrsDay_3East":null,"actualHC_3East":null,"actualOT_3East":null,"actualNpHrs_3East":null,"modelHrsDay_3East":null,"varianceHrs_3East":null,"variancePct_3East":null,"actualHrsDay_3West":null,"actualHC_3West":null,"actualOT_3West":null,"actualNpHrs_3West":null,"modelHrsDay_3West":null,"varianceHrs_3West":null,"variancePct_3West":null,"actualHrsDay_HRC":null,"actualHC_HRC":null,"actualOT_HRC":null,"actualNpHrs_HRC":null,"modelHrsDay_HRC":null,"varianceHrs_HRC":null,"variancePct_HRC":null,"TimeEntryDate":"2026-03-04"},{"date":"4/3/2026","modified":"2026-04-03T14:20:02Z","totalCensus":null,"occupancyPct":null,"census1East":null,"census2East":null,"census2West":null,"census3East":null,"census3West":null,"censusHRC":null,"occPct1East":null,"occPct2East":null,"occPct2West":null,"occPct3East":null,"occPct3West":null,"occPctHRC":null,"obsHrs":null,"modelDcEpob":null,"modelTotalEpob":null,"modelVarHrsDay":null,"varAdjFTE":null,"fixedFTE":null,"grandAdjFTE":null,"actualVarHrsDay":null,"actualFixHrsDay":null,"actualOtTotal":null,"actualVarFTE":null,"actualFixFTE":null,"actualTotalFTE":null,"actualDcEpob":null,"actualTotalEpob":null,"varianceHrsDay":null,"variancePct":null,"dcEpobVariance":null,"totalEpobVariance":null,"hasPayrollData":null,"payrollFile":null,"actualHrsDay_1East":null,"actualHC_1East":null,"actualOT_1East":null,"actualNpHrs_1East":null,"modelHrsDay_1East":null,"varianceHrs_1East":null,"variancePct_1East":null,"actualHrsDay_2East":null,"actualHC_2East":null,"actualOT_2East":null,"actualNpHrs_2East":null,"modelHrsDay_2East":null,"varianceHrs_2East":null,"variancePct_2East":null,"actualHrsDay_2West":null,"actualHC_2West":null,"actualOT_2West":null,"actualNpHrs_2West":null,"modelHrsDay_2West":null,"varianceHrs_2West":null,"variancePct_2West":null,"actualHrsDay_3East":null,"actualHC_3East":null,"actualOT_3East":null,"actualNpHrs_3East":null,"modelHrsDay_3East":null,"varianceHrs_3East":null,"variancePct_3East":null,"actualHrsDay_3West":null,"actualHC_3West":null,"actualOT_3West":null,"actualNpHrs_3West":null,"modelHrsDay_3West":null,"varianceHrs_3West":null,"variancePct_3West":null,"actualHrsDay_HRC":null,"actualHC_HRC":null,"actualOT_HRC":null,"actualNpHrs_HRC":null,"modelHrsDay_HRC":null,"varianceHrs_HRC":null,"variancePct_HRC":null,"TimeEntryDate":"2026-03-06"},{"date":"4/3/2026","modified":"2026-04-03T16:26:51Z","totalCensus":null,"occupancyPct":null,"census1East":null,"census2East":null,"census2West":null,"census3East":null,"census3West":null,"censusHRC":null,"occPct1East":null,"occPct2East":null,"occPct2West":null,"occPct3East":null,"occPct3West":null,"occPctHRC":null,"obsHrs":null,"modelDcEpob":null,"modelTotalEpob":null,"modelVarHrsDay":null,"varAdjFTE":null,"fixedFTE":null,"grandAdjFTE":null,"actualVarHrsDay":null,"actualFixHrsDay":null,"actualOtTotal":null,"actualVarFTE":null,"actualFixFTE":null,"actualTotalFTE":null,"actualDcEpob":null,"actualTotalEpob":null,"varianceHrsDay":null,"variancePct":null,"dcEpobVariance":null,"totalEpobVariance":null,"hasPayrollData":null,"payrollFile":null,"actualHrsDay_1East":null,"actualHC_1East":null,"actualOT_1East":null,"actualNpHrs_1East":null,"modelHrsDay_1East":null,"varianceHrs_1East":null,"variancePct_1East":null,"actualHrsDay_2East":null,"actualHC_2East":null,"actualOT_2East":null,"actualNpHrs_2East":null,"modelHrsDay_2East":null,"varianceHrs_2East":null,"variancePct_2East":null,"actualHrsDay_2West":null,"actualHC_2West":null,"actualOT_2West":null,"actualNpHrs_2West":null,"modelHrsDay_2West":null,"varianceHrs_2West":null,"variancePct_2West":null,"actualHrsDay_3East":null,"actualHC_3East":null,"actualOT_3East":null,"actualNpHrs_3East":null,"modelHrsDay_3East":null,"varianceHrs_3East":null,"variancePct_3East":null,"actualHrsDay_3West":null,"actualHC_3West":null,"actualOT_3West":null,"actualNpHrs_3West":null,"modelHrsDay_3West":null,"varianceHrs_3West":null,"variancePct_3West":null,"actualHrsDay_HRC":null,"actualHC_HRC":null,"actualOT_HRC":null,"actualNpHrs_HRC":null,"modelHrsDay_HRC":null,"varianceHrs_HRC":null,"variancePct_HRC":null,"TimeEntryDate":"2026-03-05"},{"date":"4/3/2026","modified":"2026-04-03T18:19:58Z","totalCensus":null,"occupancyPct":null,"census1East":null,"census2East":null,"census2West":null,"census3East":null,"census3West":null,"censusHRC":null,"occPct1East":null,"occPct2East":null,"occPct2West":null,"occPct3East":null,"occPct3West":null,"occPctHRC":null,"obsHrs":null,"modelDcEpob":null,"modelTotalEpob":null,"modelVarHrsDay":null,"varAdjFTE":null,"fixedFTE":null,"grandAdjFTE":null,"actualVarHrsDay":null,"actualFixHrsDay":null,"actualOtTotal":null,"actualVarFTE":null,"actualFixFTE":null,"actualTotalFTE":null,"actualDcEpob":null,"actualTotalEpob":null,"varianceHrsDay":null,"variancePct":null,"dcEpobVariance":null,"totalEpobVariance":null,"hasPayrollData":null,"payrollFile":null,"actualHrsDay_1East":null,"actualHC_1East":null,"actualOT_1East":null,"actualNpHrs_1East":null,"modelHrsDay_1East":null,"varianceHrs_1East":null,"variancePct_1East":null,"actualHrsDay_2East":null,"actualHC_2East":null,"actualOT_2East":null,"actualNpHrs_2East":null,"modelHrsDay_2East":null,"varianceHrs_2East":null,"variancePct_2East":null,"actualHrsDay_2West":null,"actualHC_2West":null,"actualOT_2West":null,"actualNpHrs_2West":null,"modelHrsDay_2West":null,"varianceHrs_2West":null,"variancePct_2West":null,"actualHrsDay_3East":null,"actualHC_3East":null,"actualOT_3East":null,"actualNpHrs_3East":null,"modelHrsDay_3East":null,"varianceHrs_3East":null,"variancePct_3East":null,"actualHrsDay_3West":null,"actualHC_3West":null,"actualOT_3West":null,"actualNpHrs_3West":null,"modelHrsDay_3West":null,"varianceHrs_3West":null,"variancePct_3West":null,"actualHrsDay_HRC":null,"actualHC_HRC":null,"actualOT_HRC":null,"actualNpHrs_HRC":null,"modelHrsDay_HRC":null,"varianceHrs_HRC":null,"variancePct_HRC":null,"TimeEntryDate":"2026-03-07"},{"date":"4/3/2026","modified":"2026-04-03T18:22:16Z","totalCensus":null,"occupancyPct":null,"census1East":null,"census2East":null,"census2West":null,"census3East":null,"census3West":null,"censusHRC":null,"occPct1East":null,"occPct2East":null,"occPct2West":null,"occPct3East":null,"occPct3West":null,"occPctHRC":null,"obsHrs":null,"modelDcEpob":null,"modelTotalEpob":null,"modelVarHrsDay":null,"varAdjFTE":null,"fixedFTE":null,"grandAdjFTE":null,"actualVarHrsDay":null,"actualFixHrsDay":null,"actualOtTotal":null,"actualVarFTE":null,"actualFixFTE":null,"actualTotalFTE":null,"actualDcEpob":null,"actualTotalEpob":null,"varianceHrsDay":null,"variancePct":null,"dcEpobVariance":null,"totalEpobVariance":null,"hasPayrollData":null,"payrollFile":null,"actualHrsDay_1East":null,"actualHC_1East":null,"actualOT_1East":null,"actualNpHrs_1East":null,"modelHrsDay_1East":null,"varianceHrs_1East":null,"variancePct_1East":null,"actualHrsDay_2East":null,"actualHC_2East":null,"actualOT_2East":null,"actualNpHrs_2East":null,"modelHrsDay_2East":null,"varianceHrs_2East":null,"variancePct_2East":null,"actualHrsDay_2West":null,"actualHC_2West":null,"actualOT_2West":null,"actualNpHrs_2West":null,"modelHrsDay_2West":null,"varianceHrs_2West":null,"variancePct_2West":null,"actualHrsDay_3East":null,"actualHC_3East":null,"actualOT_3East":null,"actualNpHrs_3East":null,"modelHrsDay_3East":null,"varianceHrs_3East":null,"variancePct_3East":null,"actualHrsDay_3West":null,"actualHC_3West":null,"actualOT_3West":null,"actualNpHrs_3West":null,"modelHrsDay_3West":null,"varianceHrs_3West":null,"variancePct_3West":null,"actualHrsDay_HRC":null,"actualHC_HRC":null,"actualOT_HRC":null,"actualNpHrs_HRC":null,"modelHrsDay_HRC":null,"varianceHrs_HRC":null,"variancePct_HRC":null,"TimeEntryDate":"2026-03-08"},{"date":"4/3/2026","modified":"2026-04-03T18:24:20Z","totalCensus":null,"occupancyPct":null,"census1East":null,"census2East":null,"census2West":null,"census3East":null,"census3West":null,"censusHRC":null,"occPct1East":null,"occPct2East":null,"occPct2West":null,"occPct3East":null,"occPct3West":null,"occPctHRC":null,"obsHrs":null,"modelDcEpob":null,"modelTotalEpob":null,"modelVarHrsDay":null,"varAdjFTE":null,"fixedFTE":null,"grandAdjFTE":null,"actualVarHrsDay":null,"actualFixHrsDay":null,"actualOtTotal":null,"actualVarFTE":null,"actualFixFTE":null,"actualTotalFTE":null,"actualDcEpob":null,"actualTotalEpob":null,"varianceHrsDay":null,"variancePct":null,"dcEpobVariance":null,"totalEpobVariance":null,"hasPayrollData":null,"payrollFile":null,"actualHrsDay_1East":null,"actualHC_1East":null,"actualOT_1East":null,"actualNpHrs_1East":null,"modelHrsDay_1East":null,"varianceHrs_1East":null,"variancePct_1East":null,"actualHrsDay_2East":null,"actualHC_2East":null,"actualOT_2East":null,"actualNpHrs_2East":null,"modelHrsDay_2East":null,"varianceHrs_2East":null,"variancePct_2East":null,"actualHrsDay_2West":null,"actualHC_2West":null,"actualOT_2West":null,"actualNpHrs_2West":null,"modelHrsDay_2West":null,"varianceHrs_2West":null,"variancePct_2West":null,"actualHrsDay_3East":null,"actualHC_3East":null,"actualOT_3East":null,"actualNpHrs_3East":null,"modelHrsDay_3East":null,"varianceHrs_3East":null,"variancePct_3East":null,"actualHrsDay_3West":null,"actualHC_3West":null,"actualOT_3West":null,"actualNpHrs_3West":null,"modelHrsDay_3West":null,"varianceHrs_3West":null,"variancePct_3West":null,"actualHrsDay_HRC":null,"actualHC_HRC":null,"actualOT_HRC":null,"actualNpHrs_HRC":null,"modelHrsDay_HRC":null,"varianceHrs_HRC":null,"variancePct_HRC":null,"TimeEntryDate":"2026-03-09"},{"date":"4/3/2026","modified":"2026-04-03T18:27:43Z","totalCensus":null,"occupancyPct":null,"census1East":null,"census2East":null,"census2West":null,"census3East":null,"census3West":null,"censusHRC":null,"occPct1East":null,"occPct2East":null,"occPct2West":null,"occPct3East":null,"occPct3West":null,"occPctHRC":null,"obsHrs":null,"modelDcEpob":null,"modelTotalEpob":null,"modelVarHrsDay":null,"varAdjFTE":null,"fixedFTE":null,"grandAdjFTE":null,"actualVarHrsDay":null,"actualFixHrsDay":null,"actualOtTotal":null,"actualVarFTE":null,"actualFixFTE":null,"actualTotalFTE":null,"actualDcEpob":null,"actualTotalEpob":null,"varianceHrsDay":null,"variancePct":null,"dcEpobVariance":null,"totalEpobVariance":null,"hasPayrollData":null,"payrollFile":null,"actualHrsDay_1East":null,"actualHC_1East":null,"actualOT_1East":null,"actualNpHrs_1East":null,"modelHrsDay_1East":null,"varianceHrs_1East":null,"variancePct_1East":null,"actualHrsDay_2East":null,"actualHC_2East":null,"actualOT_2East":null,"actualNpHrs_2East":null,"modelHrsDay_2East":null,"varianceHrs_2East":null,"variancePct_2East":null,"actualHrsDay_2West":null,"actualHC_2West":null,"actualOT_2West":null,"actualNpHrs_2West":null,"modelHrsDay_2West":null,"varianceHrs_2West":null,"variancePct_2West":null,"actualHrsDay_3East":null,"actualHC_3East":null,"actualOT_3East":null,"actualNpHrs_3East":null,"modelHrsDay_3East":null,"varianceHrs_3East":null,"variancePct_3East":null,"actualHrsDay_3West":null,"actualHC_3West":null,"actualOT_3West":null,"actualNpHrs_3West":null,"modelHrsDay_3West":null,"varianceHrs_3West":null,"variancePct_3West":null,"actualHrsDay_HRC":null,"actualHC_HRC":null,"actualOT_HRC":null,"actualNpHrs_HRC":null,"modelHrsDay_HRC":null,"varianceHrs_HRC":null,"variancePct_HRC":null,"TimeEntryDate":"2026-03-07"},{"date":"4/3/2026","modified":"2026-04-03T18:27:44Z","totalCensus":null,"occupancyPct":null,"census1East":null,"census2East":null,"census2West":null,"census3East":null,"census3West":null,"censusHRC":null,"occPct1East":null,"occPct2East":null,"occPct2West":null,"occPct3East":null,"occPct3West":null,"occPctHRC":null,"obsHrs":null,"modelDcEpob":null,"modelTotalEpob":null,"modelVarHrsDay":null,"varAdjFTE":null,"fixedFTE":null,"grandAdjFTE":null,"actualVarHrsDay":null,"actualFixHrsDay":null,"actualOtTotal":null,"actualVarFTE":null,"actualFixFTE":null,"actualTotalFTE":null,"actualDcEpob":null,"actualTotalEpob":null,"varianceHrsDay":null,"variancePct":null,"dcEpobVariance":null,"totalEpobVariance":null,"hasPayrollData":null,"payrollFile":null,"actualHrsDay_1East":null,"actualHC_1East":null,"actualOT_1East":null,"actualNpHrs_1East":null,"modelHrsDay_1East":null,"varianceHrs_1East":null,"variancePct_1East":null,"actualHrsDay_2East":null,"actualHC_2East":null,"actualOT_2East":null,"actualNpHrs_2East":null,"modelHrsDay_2East":null,"varianceHrs_2East":null,"variancePct_2East":null,"actualHrsDay_2West":null,"actualHC_2West":null,"actualOT_2West":null,"actualNpHrs_2West":null,"modelHrsDay_2West":null,"varianceHrs_2West":null,"variancePct_2West":null,"actualHrsDay_3East":null,"actualHC_3East":null,"actualOT_3East":null,"actualNpHrs_3East":null,"modelHrsDay_3East":null,"varianceHrs_3East":null,"variancePct_3East":null,"actualHrsDay_3West":null,"actualHC_3West":null,"actualOT_3West":null,"actualNpHrs_3West":null,"modelHrsDay_3West":null,"varianceHrs_3West":null,"variancePct_3West":null,"actualHrsDay_HRC":null,"actualHC_HRC":null,"actualOT_HRC":null,"actualNpHrs_HRC":null,"modelHrsDay_HRC":null,"varianceHrs_HRC":null,"variancePct_HRC":null,"TimeEntryDate":"2026-03-10"},{"date":"4/3/2026","modified":"2026-04-03T18:49:05Z","totalCensus":null,"occupancyPct":null,"census1East":null,"census2East":null,"census2West":null,"census3East":null,"census3West":null,"censusHRC":null,"occPct1East":null,"occPct2East":null,"occPct2West":null,"occPct3East":null,"occPct3West":null,"occPctHRC":null,"obsHrs":null,"modelDcEpob":null,"modelTotalEpob":null,"modelVarHrsDay":null,"varAdjFTE":null,"fixedFTE":null,"grandAdjFTE":null,"actualVarHrsDay":null,"actualFixHrsDay":null,"actualOtTotal":null,"actualVarFTE":null,"actualFixFTE":null,"actualTotalFTE":null,"actualDcEpob":null,"actualTotalEpob":null,"varianceHrsDay":null,"variancePct":null,"dcEpobVariance":null,"totalEpobVariance":null,"hasPayrollData":null,"payrollFile":null,"actualHrsDay_1East":null,"actualHC_1East":null,"actualOT_1East":null,"actualNpHrs_1East":null,"modelHrsDay_1East":null,"varianceHrs_1East":null,"variancePct_1East":null,"actualHrsDay_2East":null,"actualHC_2East":null,"actualOT_2East":null,"actualNpHrs_2East":null,"modelHrsDay_2East":null,"varianceHrs_2East":null,"variancePct_2East":null,"actualHrsDay_2West":null,"actualHC_2West":null,"actualOT_2West":null,"actualNpHrs_2West":null,"modelHrsDay_2West":null,"varianceHrs_2West":null,"variancePct_2West":null,"actualHrsDay_3East":null,"actualHC_3East":null,"actualOT_3East":null,"actualNpHrs_3East":null,"modelHrsDay_3East":null,"varianceHrs_3East":null,"variancePct_3East":null,"actualHrsDay_3West":null,"actualHC_3West":null,"actualOT_3West":null,"actualNpHrs_3West":null,"modelHrsDay_3West":null,"varianceHrs_3West":null,"variancePct_3West":null,"actualHrsDay_HRC":null,"actualHC_HRC":null,"actualOT_HRC":null,"actualNpHrs_HRC":null,"modelHrsDay_HRC":null,"varianceHrs_HRC":null,"variancePct_HRC":null,"TimeEntryDate":"2026-03-11"},{"date":"4/3/2026","modified":"2026-04-03T18:51:22Z","totalCensus":null,"occupancyPct":null,"census1East":null,"census2East":null,"census2West":null,"census3East":null,"census3West":null,"censusHRC":null,"occPct1East":null,"occPct2East":null,"occPct2West":null,"occPct3East":null,"occPct3West":null,"occPctHRC":null,"obsHrs":null,"modelDcEpob":null,"modelTotalEpob":null,"modelVarHrsDay":null,"varAdjFTE":null,"fixedFTE":null,"grandAdjFTE":null,"actualVarHrsDay":null,"actualFixHrsDay":null,"actualOtTotal":null,"actualVarFTE":null,"actualFixFTE":null,"actualTotalFTE":null,"actualDcEpob":null,"actualTotalEpob":null,"varianceHrsDay":null,"variancePct":null,"dcEpobVariance":null,"totalEpobVariance":null,"hasPayrollData":null,"payrollFile":null,"actualHrsDay_1East":null,"actualHC_1East":null,"actualOT_1East":null,"actualNpHrs_1East":null,"modelHrsDay_1East":null,"varianceHrs_1East":null,"variancePct_1East":null,"actualHrsDay_2East":null,"actualHC_2East":null,"actualOT_2East":null,"actualNpHrs_2East":null,"modelHrsDay_2East":null,"varianceHrs_2East":null,"variancePct_2East":null,"actualHrsDay_2West":null,"actualHC_2West":null,"actualOT_2West":null,"actualNpHrs_2West":null,"modelHrsDay_2West":null,"varianceHrs_2West":null,"variancePct_2West":null,"actualHrsDay_3East":null,"actualHC_3East":null,"actualOT_3East":null,"actualNpHrs_3East":null,"modelHrsDay_3East":null,"varianceHrs_3East":null,"variancePct_3East":null,"actualHrsDay_3West":null,"actualHC_3West":null,"actualOT_3West":null,"actualNpHrs_3West":null,"modelHrsDay_3West":null,"varianceHrs_3West":null,"variancePct_3West":null,"actualHrsDay_HRC":null,"actualHC_HRC":null,"actualOT_HRC":null,"actualNpHrs_HRC":null,"modelHrsDay_HRC":null,"varianceHrs_HRC":null,"variancePct_HRC":null,"TimeEntryDate":"2026-03-12"},{"date":"4/3/2026","modified":"2026-04-03T18:54:00Z","totalCensus":null,"occupancyPct":null,"census1East":null,"census2East":null,"census2West":null,"census3East":null,"census3West":null,"censusHRC":null,"occPct1East":null,"occPct2East":null,"occPct2West":null,"occPct3East":null,"occPct3West":null,"occPctHRC":null,"obsHrs":null,"modelDcEpob":null,"modelTotalEpob":null,"modelVarHrsDay":null,"varAdjFTE":null,"fixedFTE":null,"grandAdjFTE":null,"actualVarHrsDay":null,"actualFixHrsDay":null,"actualOtTotal":null,"actualVarFTE":null,"actualFixFTE":null,"actualTotalFTE":null,"actualDcEpob":null,"actualTotalEpob":null,"varianceHrsDay":null,"variancePct":null,"dcEpobVariance":null,"totalEpobVariance":null,"hasPayrollData":null,"payrollFile":null,"actualHrsDay_1East":null,"actualHC_1East":null,"actualOT_1East":null,"actualNpHrs_1East":null,"modelHrsDay_1East":null,"varianceHrs_1East":null,"variancePct_1East":null,"actualHrsDay_2East":null,"actualHC_2East":null,"actualOT_2East":null,"actualNpHrs_2East":null,"modelHrsDay_2East":null,"varianceHrs_2East":null,"variancePct_2East":null,"actualHrsDay_2West":null,"actualHC_2West":null,"actualOT_2West":null,"actualNpHrs_2West":null,"modelHrsDay_2West":null,"varianceHrs_2West":null,"variancePct_2West":null,"actualHrsDay_3East":null,"actualHC_3East":null,"actualOT_3East":null,"actualNpHrs_3East":null,"modelHrsDay_3East":null,"varianceHrs_3East":null,"variancePct_3East":null,"actualHrsDay_3West":null,"actualHC_3West":null,"actualOT_3West":null,"actualNpHrs_3West":null,"modelHrsDay_3West":null,"varianceHrs_3West":null,"variancePct_3West":null,"actualHrsDay_HRC":null,"actualHC_HRC":null,"actualOT_HRC":null,"actualNpHrs_HRC":null,"modelHrsDay_HRC":null,"varianceHrs_HRC":null,"variancePct_HRC":null,"TimeEntryDate":"2026-03-13"},{"date":"4/3/2026","modified":"2026-04-03T18:56:17Z","totalCensus":null,"occupancyPct":null,"census1East":null,"census2East":null,"census2West":null,"census3East":null,"census3West":null,"censusHRC":null,"occPct1East":null,"occPct2East":null,"occPct2West":null,"occPct3East":null,"occPct3West":null,"occPctHRC":null,"obsHrs":null,"modelDcEpob":null,"modelTotalEpob":null,"modelVarHrsDay":null,"varAdjFTE":null,"fixedFTE":null,"grandAdjFTE":null,"actualVarHrsDay":null,"actualFixHrsDay":null,"actualOtTotal":null,"actualVarFTE":null,"actualFixFTE":null,"actualTotalFTE":null,"actualDcEpob":null,"actualTotalEpob":null,"varianceHrsDay":null,"variancePct":null,"dcEpobVariance":null,"totalEpobVariance":null,"hasPayrollData":null,"payrollFile":null,"actualHrsDay_1East":null,"actualHC_1East":null,"actualOT_1East":null,"actualNpHrs_1East":null,"modelHrsDay_1East":null,"varianceHrs_1East":null,"variancePct_1East":null,"actualHrsDay_2East":null,"actualHC_2East":null,"actualOT_2East":null,"actualNpHrs_2East":null,"modelHrsDay_2East":null,"varianceHrs_2East":null,"variancePct_2East":null,"actualHrsDay_2West":null,"actualHC_2West":null,"actualOT_2West":null,"actualNpHrs_2West":null,"modelHrsDay_2West":null,"varianceHrs_2West":null,"variancePct_2West":null,"actualHrsDay_3East":null,"actualHC_3East":null,"actualOT_3East":null,"actualNpHrs_3East":null,"modelHrsDay_3East":null,"varianceHrs_3East":null,"variancePct_3East":null,"actualHrsDay_3West":null,"actualHC_3West":null,"actualOT_3West":null,"actualNpHrs_3West":null,"modelHrsDay_3West":null,"varianceHrs_3West":null,"variancePct_3West":null,"actualHrsDay_HRC":null,"actualHC_HRC":null,"actualOT_HRC":null,"actualNpHrs_HRC":null,"modelHrsDay_HRC":null,"varianceHrs_HRC":null,"variancePct_HRC":null,"TimeEntryDate":"2026-03-14"},{"date":"4/3/2026","modified":"2026-04-03T19:07:28Z","totalCensus":null,"occupancyPct":null,"census1East":null,"census2East":null,"census2West":null,"census3East":null,"census3West":null,"censusHRC":null,"occPct1East":null,"occPct2East":null,"occPct2West":null,"occPct3East":null,"occPct3West":null,"occPctHRC":null,"obsHrs":null,"modelDcEpob":null,"modelTotalEpob":null,"modelVarHrsDay":null,"varAdjFTE":null,"fixedFTE":null,"grandAdjFTE":null,"actualVarHrsDay":null,"actualFixHrsDay":null,"actualOtTotal":null,"actualVarFTE":null,"actualFixFTE":null,"actualTotalFTE":null,"actualDcEpob":null,"actualTotalEpob":null,"varianceHrsDay":null,"variancePct":null,"dcEpobVariance":null,"totalEpobVariance":null,"hasPayrollData":null,"payrollFile":null,"actualHrsDay_1East":null,"actualHC_1East":null,"actualOT_1East":null,"actualNpHrs_1East":null,"modelHrsDay_1East":null,"varianceHrs_1East":null,"variancePct_1East":null,"actualHrsDay_2East":null,"actualHC_2East":null,"actualOT_2East":null,"actualNpHrs_2East":null,"modelHrsDay_2East":null,"varianceHrs_2East":null,"variancePct_2East":null,"actualHrsDay_2West":null,"actualHC_2West":null,"actualOT_2West":null,"actualNpHrs_2West":null,"modelHrsDay_2West":null,"varianceHrs_2West":null,"variancePct_2West":null,"actualHrsDay_3East":null,"actualHC_3East":null,"actualOT_3East":null,"actualNpHrs_3East":null,"modelHrsDay_3East":null,"varianceHrs_3East":null,"variancePct_3East":null,"actualHrsDay_3West":null,"actualHC_3West":null,"actualOT_3West":null,"actualNpHrs_3West":null,"modelHrsDay_3West":null,"varianceHrs_3West":null,"variancePct_3West":null,"actualHrsDay_HRC":null,"actualHC_HRC":null,"actualOT_HRC":null,"actualNpHrs_HRC":null,"modelHrsDay_HRC":null,"varianceHrs_HRC":null,"variancePct_HRC":null,"TimeEntryDate":"2026-03-15"},{"date":"4/3/2026","modified":"2026-04-03T19:27:31Z","totalCensus":null,"occupancyPct":null,"census1East":null,"census2East":null,"census2West":null,"census3East":null,"census3West":null,"censusHRC":null,"occPct1East":null,"occPct2East":null,"occPct2West":null,"occPct3East":null,"occPct3West":null,"occPctHRC":null,"obsHrs":null,"modelDcEpob":null,"modelTotalEpob":null,"modelVarHrsDay":null,"varAdjFTE":null,"fixedFTE":null,"grandAdjFTE":null,"actualVarHrsDay":null,"actualFixHrsDay":null,"actualOtTotal":null,"actualVarFTE":null,"actualFixFTE":null,"actualTotalFTE":null,"actualDcEpob":null,"actualTotalEpob":null,"varianceHrsDay":null,"variancePct":null,"dcEpobVariance":null,"totalEpobVariance":null,"hasPayrollData":null,"payrollFile":null,"actualHrsDay_1East":null,"actualHC_1East":null,"actualOT_1East":null,"actualNpHrs_1East":null,"modelHrsDay_1East":null,"varianceHrs_1East":null,"variancePct_1East":null,"actualHrsDay_2East":null,"actualHC_2East":null,"actualOT_2East":null,"actualNpHrs_2East":null,"modelHrsDay_2East":null,"varianceHrs_2East":null,"variancePct_2East":null,"actualHrsDay_2West":null,"actualHC_2West":null,"actualOT_2West":null,"actualNpHrs_2West":null,"modelHrsDay_2West":null,"varianceHrs_2West":null,"variancePct_2West":null,"actualHrsDay_3East":null,"actualHC_3East":null,"actualOT_3East":null,"actualNpHrs_3East":null,"modelHrsDay_3East":null,"varianceHrs_3East":null,"variancePct_3East":null,"actualHrsDay_3West":null,"actualHC_3West":null,"actualOT_3West":null,"actualNpHrs_3West":null,"modelHrsDay_3West":null,"varianceHrs_3West":null,"variancePct_3West":null,"actualHrsDay_HRC":null,"actualHC_HRC":null,"actualOT_HRC":null,"actualNpHrs_HRC":null,"modelHrsDay_HRC":null,"varianceHrs_HRC":null,"variancePct_HRC":null,"TimeEntryDate":"2026-04-02"},{"date":"4/6/2026","modified":"2026-04-06T16:11:02Z","totalCensus":null,"occupancyPct":null,"census1East":null,"census2East":null,"census2West":null,"census3East":null,"census3West":null,"censusHRC":null,"occPct1East":null,"occPct2East":null,"occPct2West":null,"occPct3East":null,"occPct3West":null,"occPctHRC":null,"obsHrs":null,"modelDcEpob":null,"modelTotalEpob":null,"modelVarHrsDay":null,"varAdjFTE":null,"fixedFTE":null,"grandAdjFTE":null,"actualVarHrsDay":null,"actualFixHrsDay":null,"actualOtTotal":null,"actualVarFTE":null,"actualFixFTE":null,"actualTotalFTE":null,"actualDcEpob":null,"actualTotalEpob":null,"varianceHrsDay":null,"variancePct":null,"dcEpobVariance":null,"totalEpobVariance":null,"hasPayrollData":null,"payrollFile":null,"actualHrsDay_1East":null,"actualHC_1East":null,"actualOT_1East":null,"actualNpHrs_1East":null,"modelHrsDay_1East":null,"varianceHrs_1East":null,"variancePct_1East":null,"actualHrsDay_2East":null,"actualHC_2East":null,"actualOT_2East":null,"actualNpHrs_2East":null,"modelHrsDay_2East":null,"varianceHrs_2East":null,"variancePct_2East":null,"actualHrsDay_2West":null,"actualHC_2West":null,"actualOT_2West":null,"actualNpHrs_2West":null,"modelHrsDay_2West":null,"varianceHrs_2West":null,"variancePct_2West":null,"actualHrsDay_3East":null,"actualHC_3East":null,"actualOT_3East":null,"actualNpHrs_3East":null,"modelHrsDay_3East":null,"varianceHrs_3East":null,"variancePct_3East":null,"actualHrsDay_3West":null,"actualHC_3West":null,"actualOT_3West":null,"actualNpHrs_3West":null,"modelHrsDay_3West":null,"varianceHrs_3West":null,"variancePct_3West":null,"actualHrsDay_HRC":null,"actualHC_HRC":null,"actualOT_HRC":null,"actualNpHrs_HRC":null,"modelHrsDay_HRC":null,"varianceHrs_HRC":null,"variancePct_HRC":null,"TimeEntryDate":"2026-04-03"},{"date":"4/6/2026","modified":"2026-04-06T16:12:39Z","totalCensus":null,"occupancyPct":null,"census1East":null,"census2East":null,"census2West":null,"census3East":null,"census3West":null,"censusHRC":null,"occPct1East":null,"occPct2East":null,"occPct2West":null,"occPct3East":null,"occPct3West":null,"occPctHRC":null,"obsHrs":null,"modelDcEpob":null,"modelTotalEpob":null,"modelVarHrsDay":null,"varAdjFTE":null,"fixedFTE":null,"grandAdjFTE":null,"actualVarHrsDay":null,"actualFixHrsDay":null,"actualOtTotal":null,"actualVarFTE":null,"actualFixFTE":null,"actualTotalFTE":null,"actualDcEpob":null,"actualTotalEpob":null,"varianceHrsDay":null,"variancePct":null,"dcEpobVariance":null,"totalEpobVariance":null,"hasPayrollData":null,"payrollFile":null,"actualHrsDay_1East":null,"actualHC_1East":null,"actualOT_1East":null,"actualNpHrs_1East":null,"modelHrsDay_1East":null,"varianceHrs_1East":null,"variancePct_1East":null,"actualHrsDay_2East":null,"actualHC_2East":null,"actualOT_2East":null,"actualNpHrs_2East":null,"modelHrsDay_2East":null,"varianceHrs_2East":null,"variancePct_2East":null,"actualHrsDay_2West":null,"actualHC_2West":null,"actualOT_2West":null,"actualNpHrs_2West":null,"modelHrsDay_2West":null,"varianceHrs_2West":null,"variancePct_2West":null,"actualHrsDay_3East":null,"actualHC_3East":null,"actualOT_3East":null,"actualNpHrs_3East":null,"modelHrsDay_3East":null,"varianceHrs_3East":null,"variancePct_3East":null,"actualHrsDay_3West":null,"actualHC_3West":null,"actualOT_3West":null,"actualNpHrs_3West":null,"modelHrsDay_3West":null,"varianceHrs_3West":null,"variancePct_3West":null,"actualHrsDay_HRC":null,"actualHC_HRC":null,"actualOT_HRC":null,"actualNpHrs_HRC":null,"modelHrsDay_HRC":null,"varianceHrs_HRC":null,"variancePct_HRC":null,"TimeEntryDate":"2026-04-04"},{"date":"4/7/2026","modified":"2026-04-07T13:12:40Z","totalCensus":null,"occupancyPct":null,"census1East":null,"census2East":null,"census2West":null,"census3East":null,"census3West":null,"censusHRC":null,"occPct1East":null,"occPct2East":null,"occPct2West":null,"occPct3East":null,"occPct3West":null,"occPctHRC":null,"obsHrs":null,"modelDcEpob":null,"modelTotalEpob":null,"modelVarHrsDay":null,"varAdjFTE":null,"fixedFTE":null,"grandAdjFTE":null,"actualVarHrsDay":null,"actualFixHrsDay":null,"actualOtTotal":null,"actualVarFTE":null,"actualFixFTE":null,"actualTotalFTE":null,"actualDcEpob":null,"actualTotalEpob":null,"varianceHrsDay":null,"variancePct":null,"dcEpobVariance":null,"totalEpobVariance":null,"hasPayrollData":null,"payrollFile":null,"actualHrsDay_1East":null,"actualHC_1East":null,"actualOT_1East":null,"actualNpHrs_1East":null,"modelHrsDay_1East":null,"varianceHrs_1East":null,"variancePct_1East":null,"actualHrsDay_2East":null,"actualHC_2East":null,"actualOT_2East":null,"actualNpHrs_2East":null,"modelHrsDay_2East":null,"varianceHrs_2East":null,"variancePct_2East":null,"actualHrsDay_2West":null,"actualHC_2West":null,"actualOT_2West":null,"actualNpHrs_2West":null,"modelHrsDay_2West":null,"varianceHrs_2West":null,"variancePct_2West":null,"actualHrsDay_3East":null,"actualHC_3East":null,"actualOT_3East":null,"actualNpHrs_3East":null,"modelHrsDay_3East":null,"varianceHrs_3East":null,"variancePct_3East":null,"actualHrsDay_3West":null,"actualHC_3West":null,"actualOT_3West":null,"actualNpHrs_3West":null,"modelHrsDay_3West":null,"varianceHrs_3West":null,"variancePct_3West":null,"actualHrsDay_HRC":null,"actualHC_HRC":null,"actualOT_HRC":null,"actualNpHrs_HRC":null,"modelHrsDay_HRC":null,"varianceHrs_HRC":null,"variancePct_HRC":null,"TimeEntryDate":"2026-04-05"},{"date":"4/7/2026","modified":"2026-04-07T13:25:07Z","totalCensus":null,"occupancyPct":null,"census1East":null,"census2East":null,"census2West":null,"census3East":null,"census3West":null,"censusHRC":null,"occPct1East":null,"occPct2East":null,"occPct2West":null,"occPct3East":null,"occPct3West":null,"occPctHRC":null,"obsHrs":null,"modelDcEpob":null,"modelTotalEpob":null,"modelVarHrsDay":null,"varAdjFTE":null,"fixedFTE":null,"grandAdjFTE":null,"actualVarHrsDay":null,"actualFixHrsDay":null,"actualOtTotal":null,"actualVarFTE":null,"actualFixFTE":null,"actualTotalFTE":null,"actualDcEpob":null,"actualTotalEpob":null,"varianceHrsDay":null,"variancePct":null,"dcEpobVariance":null,"totalEpobVariance":null,"hasPayrollData":null,"payrollFile":null,"actualHrsDay_1East":null,"actualHC_1East":null,"actualOT_1East":null,"actualNpHrs_1East":null,"modelHrsDay_1East":null,"varianceHrs_1East":null,"variancePct_1East":null,"actualHrsDay_2East":null,"actualHC_2East":null,"actualOT_2East":null,"actualNpHrs_2East":null,"modelHrsDay_2East":null,"varianceHrs_2East":null,"variancePct_2East":null,"actualHrsDay_2West":null,"actualHC_2West":null,"actualOT_2West":null,"actualNpHrs_2West":null,"modelHrsDay_2West":null,"varianceHrs_2West":null,"variancePct_2West":null,"actualHrsDay_3East":null,"actualHC_3East":null,"actualOT_3East":null,"actualNpHrs_3East":null,"modelHrsDay_3East":null,"varianceHrs_3East":null,"variancePct_3East":null,"actualHrsDay_3West":null,"actualHC_3West":null,"actualOT_3West":null,"actualNpHrs_3West":null,"modelHrsDay_3West":null,"varianceHrs_3West":null,"variancePct_3West":null,"actualHrsDay_HRC":null,"actualHC_HRC":null,"actualOT_HRC":null,"actualNpHrs_HRC":null,"modelHrsDay_HRC":null,"varianceHrs_HRC":null,"variancePct_HRC":null,"TimeEntryDate":"2026-04-01"}]